rayvision_api/__init__.py
rayvision_api/connect.py
rayvision_api/constants.py
rayvision_api/core.py
rayvision_api/exception.py
rayvision_api/file_operator.py
rayvision_api/json_operator.py
rayvision_api/paths.py
rayvision_api/signature.py
rayvision_api/url.py
rayvision_api/utils.py
rayvision_api/validator.py
rayvision_api/operators/__init__.py
rayvision_api/operators/env.py
rayvision_api/operators/query.py
rayvision_api/operators/tag.py
rayvision_api/operators/task.py
rayvision_api/operators/transmit.py
rayvision_api/operators/user.py
rayvision_api/schemas/abandonTask.yaml
rayvision_api/schemas/add.yaml
rayvision_api/schemas/addTaskLabel.yaml
rayvision_api/schemas/addUserPluginConfig.yaml
rayvision_api/schemas/createTask.yaml
rayvision_api/schemas/delete.yaml
rayvision_api/schemas/deleteTask.yaml
rayvision_api/schemas/deleteTaskLabel.yaml
rayvision_api/schemas/deleteUserPluginConfig.yaml
rayvision_api/schemas/editTaskHardwareConfig.yaml
rayvision_api/schemas/editUserPluginConfig.yaml
rayvision_api/schemas/fullSpeedRendering.yaml
rayvision_api/schemas/getOutputUserDirFile.yaml
rayvision_api/schemas/getRaySyncUserKey.yaml
rayvision_api/schemas/getServerInfo.yaml
rayvision_api/schemas/getTaskList.yaml
rayvision_api/schemas/getUserPluginConfig.yaml
rayvision_api/schemas/list.yaml
rayvision_api/schemas/loadTaskProcessImg.yaml
rayvision_api/schemas/loadingFrameThumbnail.yaml
rayvision_api/schemas/loginRecord.yaml
rayvision_api/schemas/queryAllFrameStats.yaml
rayvision_api/schemas/queryAnalyseErrorDetail.yaml
rayvision_api/schemas/queryPlatforms.yaml
rayvision_api/schemas/querySoftwareDetail.yaml
rayvision_api/schemas/queryTaskFrames.yaml
rayvision_api/schemas/queryTaskInfo.yaml
rayvision_api/schemas/recommitTaskFrames.yaml
rayvision_api/schemas/recommitTasks.yaml
rayvision_api/schemas/schema_v1.yaml
rayvision_api/schemas/setDefaultUserPluginConfig.yaml
rayvision_api/schemas/setTaskOverTimeStop.yaml
rayvision_api/schemas/startTask.yaml
rayvision_api/schemas/stopTask.yaml
rayvision_api-3.0.4.1.dist-info/LICENSE
rayvision_api-3.0.4.1.dist-info/METADATA
rayvision_api-3.0.4.1.dist-info/WHEEL
rayvision_api-3.0.4.1.dist-info/top_level.txt
rayvision_api-3.0.4.1.dist-info/RECORD
