Metadata-Version: 2.1
Name: rayvision-api
Version: 3.0.4.1
Summary: A Python-based API for Using Renderbus cloud rendering service.
Home-page: https://gitlab.renderbus.com/internal/rayvision_api
Author: Shenzhen Rayvision Technology Co., Ltd
Author-email: developer@rayvision.com
Classifier: Programming Language :: Python
Classifier: Programming Language :: Python :: 2
Classifier: Programming Language :: Python :: 3
License-File: LICENSE
Requires-Dist: attrs ==19.3.0
Requires-Dist: cattrs ==1.0.0
Requires-Dist: tenacity ==7.0.0
Requires-Dist: future ==0.18.2
Requires-Dist: requests ==2.23.0
Requires-Dist: Cerberus
Requires-Dist: rayvision-log >=0.3.3
